linkotron/__init__.py
linkotron/__main__.py
linkotron/_version.py
linkotron/cli.py
linkotron/py.typed
linkotron/scripts/__init__.py
linkotron/scripts/run_command.py
linkotron-0.6.0.dist-info/METADATA
linkotron-0.6.0.dist-info/WHEEL
linkotron-0.6.0.dist-info/entry_points.txt
linkotron-0.6.0.dist-info/licenses/LICENSE.txt
linkotron-0.6.0.dist-info/RECORD
