Metadata-Version: 2.4
Name: linkotron
Version: 0.6.0
Summary: CLI to format links
Project-URL: Changelog, https://github.com/hugovk/linkotron/releases
Project-URL: Homepage, https://github.com/hugovk/linkotron
Project-URL: Issue tracker, https://github.com/hugovk/linkotron/issues
Project-URL: Release notes, https://github.com/hugovk/linkotron/releases
Project-URL: Source, https://github.com/hugovk/linkotron
Author: Hugo van Kemenade
License-Expression: MIT
License-File: LICENSE.txt
Keywords: link,markdown,md,restructuredtext,rst
Classifier: Development Status :: 3 - Alpha
Classifier: Intended Audience :: Developers
Classifier: Intended Audience :: End Users/Desktop
Classifier: Operating System :: OS Independent
Classifier: Programming Language :: Python :: 3 :: Only
Classifier: Programming Language :: Python :: 3.10
Classifier: Programming Language :: Python :: 3.11
Classifier: Programming Language :: Python :: 3.12
Classifier: Programming Language :: Python :: 3.13
Classifier: Programming Language :: Python :: 3.14
Classifier: Programming Language :: Python :: Implementation :: CPython
Classifier: Programming Language :: Python :: Implementation :: PyPy
Requires-Python: >=3.10
Requires-Dist: pyperclip; platform_system == 'Darwin'
Requires-Dist: pyperclip; platform_system == 'Windows'
Provides-Extra: tests
Requires-Dist: pytest; extra == 'tests'
Requires-Dist: pytest-cov; extra == 'tests'
